setup.py
cine_io/__init__.py
cine_io/cine_io.py
cine_io/version.py
cine_io.egg-info/PKG-INFO
cine_io.egg-info/SOURCES.txt
cine_io.egg-info/dependency_links.txt
cine_io.egg-info/requires.txt
cine_io.egg-info/top_level.txt