Metadata-Version: 1.1
Name: cine-io
Version: 0.1.2
Summary: cine.io is an api driven platform for creating and publish live streams. The provides cine.io functionality using your given public and secret keys.
Home-page: https://www.cine.io
Author: Cine.io Engineering
Author-email: engineering@cine.io
License: MIT
Platform: UNKNOWN
Classifier: License :: OSI Approved :: MIT License
Classifier: Programming Language :: Python
Classifier: Development Status :: 3 - Alpha
Classifier: Intended Audience :: Developers
Classifier: Topic :: Internet
